splynters-0.1.2.dist-info/METADATA
splynters-0.1.2.dist-info/WHEEL
splynters-0.1.2.dist-info/licenses/LICENSE
splynters/__init__.py
splynters/splynters.cpython-310-darwin.so
splynters-0.1.2.dist-info/RECORD
