Metadata-Version: 2.4
Name: splynters
Version: 0.1.2
Classifier: Development Status :: 4 - Beta
Classifier: Programming Language :: Rust
Classifier: Programming Language :: Python :: 3
Classifier: Programming Language :: Python :: Implementation :: CPython
Classifier: Programming Language :: Python :: Implementation :: PyPy
Classifier: Topic :: Scientific/Engineering :: Information Analysis
Classifier: Topic :: System :: Archiving :: Compression
Classifier: Operating System :: OS Independent
Classifier: Intended Audience :: Developers
Classifier: License :: OSI Approved :: Apache Software License
License-File: LICENSE
Summary: A Python frontend for the splinter-rs bitmap compression library
Keywords: compression,roaring
Author-email: Nicolas Roman Posner <nrposner@uchicago.edu>
Maintainer-email: Nicolas Roman Posner <nrposner@uchicago.edu>
Requires-Python: >=3.8
Project-URL: repository, https://github.com/nrposner/splynters
